prim/__init__.py
prim/exceptions.py
prim/plotting_util.py
prim/prim_alg.py
prim/prim_box.py
prim/prim_objfcn.py
prim/prim_ops.py
prim/scenario_discovery_util.py
prim/test/__init__.py
prim/test/test_prim.py
PRIM-1.0.0.dist-info/COPYING
PRIM-1.0.0.dist-info/METADATA
PRIM-1.0.0.dist-info/WHEEL
PRIM-1.0.0.dist-info/top_level.txt
PRIM-1.0.0.dist-info/RECORD
