Metadata-Version: 2.1
Name: PRIM
Version: 1.0.0
Summary: Patient Rule Induction Method for Python
Author-email: David Hadka <dhadka@users.noreply.github.com>
License: GNU GENERAL PUBLIC LICENSE
Project-URL: Homepage, https://github.com/Project-Platypus/PRIM
Project-URL: Bug Tracker, https://github.com/Project-Platypus/PRIM/issues
Requires-Python: >=3.8
License-File: COPYING
Requires-Dist: matplotlib
Requires-Dist: numpy
Requires-Dist: pandas
Requires-Dist: mplcursors
Requires-Dist: scipy
Provides-Extra: test
Requires-Dist: pytest ; extra == 'test'
Requires-Dist: mock ; extra == 'test'
